gendev/__init__.py
gendev/gendev.py
gendev-0.0.1.dist-info/LICENSE
gendev-0.0.1.dist-info/METADATA
gendev-0.0.1.dist-info/WHEEL
gendev-0.0.1.dist-info/entry_points.txt
gendev-0.0.1.dist-info/top_level.txt
gendev-0.0.1.dist-info/RECORD
